LICENSE
MANIFEST.in
README
setup.cfg
setup.py
bin/telemetry
example/__init__.py
example/__main__.py
telemetry/__init__.py
telemetry/__main__.py
telemetry/default.py
telemetry/deprecated.py
telemetry/load_utils.py
telemetry/registry.py
telemetry/with.py
telemetry/wrappers.py
telemetry.egg-info/PKG-INFO
telemetry.egg-info/SOURCES.txt
telemetry.egg-info/dependency_links.txt
telemetry.egg-info/requires.txt
telemetry.egg-info/top_level.txt
telemetry/clients/__init__.py
telemetry/clients/default.py
telemetry/clients/dummy.py
telemetry/clients/datadog/__init__.py
telemetry/clients/datadog/__main__.py
telemetry/clients/pagerduty/__init__.py
telemetry/clients/pagerduty/__main__.py
telemetry/clients/slack/__init__.py
telemetry/clients/slack/__main__.py
telemetry/clients/statsd_/__init__.py
telemetry/clients/statsd_/__main__.py
telemetry/loggers/__init__.py
telemetry/telemeter/__init__.py
telemetry/telemeter/exceptions.py
telemetry/telemeter/decorators/__init__.py