Metadata-Version: 2.1
Name: telemetry
Version: 2.0.8
Summary: Remote measurements for your app
Home-page: http://github.com/trevorgrayson/telemetry
Author: trevor grayson
Author-email: trevor@dave.com
License: MIT
Classifier: License :: OSI Approved :: MIT License
Classifier: Programming Language :: Python
Classifier: Topic :: Software Development :: Libraries
Classifier: Topic :: System :: Monitoring
Classifier: Topic :: System :: Logging
Provides-Extra: datadog
Provides-Extra: statsd
License-File: LICENSE
